mtsl/__init__.py
mtsl/exceptions.py
mtsl/main.py
mtsl-0.1.0.6.dist-info/METADATA
mtsl-0.1.0.6.dist-info/WHEEL
mtsl-0.1.0.6.dist-info/top_level.txt
mtsl-0.1.0.6.dist-info/RECORD
