Metadata-Version: 2.4
Name: mtsl
Version: 0.1.0.6
Summary: An easy to use, minimal trust security layer.
Author: Preston Coley
Author-email: prestoncoley0920@proton.me
Classifier: Programming Language :: Python :: 3
Classifier: Operating System :: OS Independent
Requires-Python: >=3.6
Requires-Dist: pyelle>=0.1.0
Requires-Dist: cryptography>=45.0.3
Requires-Dist: argon2-cffi>=25.1.0
Dynamic: author
Dynamic: author-email
Dynamic: classifier
Dynamic: description
Dynamic: description-content-type
Dynamic: requires-dist
Dynamic: requires-python
Dynamic: summary
